{
  "$schema": "http://json-schema.org/schema#",
  "type": "object",
  "properties": {
    "impressions_history_posts_seen": {
      "type": "array",
      "items": {
        "type": "object",
        "properties": {
          "string_map_data": {
            "type": "object",
            "properties": {
              "Author": {
                "type": "object",
                "properties": {
                  "value": {
                    "type": "string"
                  }
                },
                "required": [
                  "value"
                ]
              },
              "Time": {
                "type": "object",
                "properties": {
                  "timestamp": {
                    "type": "integer"
                  }
                },
                "required": [
                  "timestamp"
                ]
              }
            },
            "required": [
              "Author",
              "Time"
            ]
          }
        },
        "required": [
          "string_map_data"
        ]
      }
    }
  },
  "required": [
    "impressions_history_posts_seen"
  ]
}

